NaughtyClustered/__init__.py
NaughtyClustered/naughty_and_nice_cluster.py
NaughtyClustered-0.3.7.dist-info/DESCRIPTION.rst
NaughtyClustered-0.3.7.dist-info/METADATA
NaughtyClustered-0.3.7.dist-info/RECORD
NaughtyClustered-0.3.7.dist-info/WHEEL
NaughtyClustered-0.3.7.dist-info/metadata.json
NaughtyClustered-0.3.7.dist-info/top_level.txt
