Metadata-Version: 2.0
Name: NaughtyClustered
Version: 0.3.7
Summary: Clustered version of Naughty and Nice with a few more addons
Home-page: UNKNOWN
Author: xXTheProgrammerXx
Author-email: arhithprem@gmail.com
License: UNKNOWN
Keywords: classifing,learning
Platform: UNKNOWN
Classifier: Development Status :: 5 - Production/Stable
Classifier: Intended Audience :: Education
Classifier: Programming Language :: Python :: 3
Requires: tweepy
Requires: nltk
Requires: dispy
